texenv/__init__.py
texenv/macros.py
texenv/packages.py
texenv/preprocessor.py
texenv/runner.py
texenv/slides.py
texenv/utils.py
texenv/pkg_files/slides.txt
texenv/templates/default.tex
texenv-0.0.10.dist-info/LICENSE.txt
texenv-0.0.10.dist-info/METADATA
texenv-0.0.10.dist-info/WHEEL
texenv-0.0.10.dist-info/entry_points.txt
texenv-0.0.10.dist-info/top_level.txt
texenv-0.0.10.dist-info/RECORD
