Metadata-Version: 2.1
Name: texenv
Version: 0.0.10
Summary: latex inside a python virtual environment
Author-email: Rick Lyon <rlyon14@gmail.com>
Project-URL: repository, https://github.com/ricklyon/texenv
Keywords: latex,tex,environment
Classifier: License :: OSI Approved :: MIT License
Classifier: Programming Language :: Python
Classifier: Programming Language :: Python :: 3
Requires-Python: >=3.7
License-File: LICENSE.txt
Requires-Dist: click
Requires-Dist: pillow
Requires-Dist: numpy
Requires-Dist: matplotlib
Provides-Extra: dev
Requires-Dist: black; extra == "dev"
Requires-Dist: flake8; extra == "dev"
Requires-Dist: pytest; extra == "dev"
